coodb/__init__.py
coodb/batch.py
coodb/db.py
coodb/errors.py
coodb/iterator.py
coodb/merge.py
coodb/options.py
coodb/data/__init__.py
coodb/data/data_file.py
coodb/data/log_record.py
coodb/fio/__init__.py
coodb/fio/file_io.py
coodb/fio/io_manager.py
coodb/fio/mmap.py
coodb/fio/mmap_io.py
coodb/http/__init__.py
coodb/http/app.py
coodb/http/run.py
coodb/http/server.py
coodb/index/__init__.py
coodb/index/art.py
coodb/index/base.py
coodb/index/bptree.py
coodb/index/btree.py
coodb/index/index.py
coodb/index/interface.py
coodb/index/skiplist.py
coodb/utils/__init__.py
coodb/utils/file.py
coodb-0.1.0.dist-info/licenses/LICENSE
coodb-0.1.0.dist-info/METADATA
coodb-0.1.0.dist-info/WHEEL
coodb-0.1.0.dist-info/top_level.txt
coodb-0.1.0.dist-info/RECORD
